<annotation>
	<folder>download</folder>
	<filename>1744887.jpg</filename>
	<path>D:\danbooru_face\download\1744887.jpg</path>
	<source>
		<database>Unknown</database>
	</source>
	<size>
		<width>3507</width>
		<height>2480</height>
		<depth>3</depth>
	</size>
	<segmented>0</segmented>
	<object>
		<name>face</name>
		<truncated>0</truncated>
		<difficult>0</difficult>
		<jingai>0</jingai>
		<blur>0</blur>
		<pose>0</pose>
		<occlusion>0</occlusion>
		<bndbox>
			<xmin>858</xmin>
			<ymin>667</ymin>
			<xmax>1183</xmax>
			<ymax>1086</ymax>
		</bndbox>
	</object>
	<object>
		<name>face</name>
		<truncated>0</truncated>
		<difficult>0</difficult>
		<jingai>0</jingai>
		<blur>0</blur>
		<pose>0</pose>
		<occlusion>0</occlusion>
		<bndbox>
			<xmin>1521</xmin>
			<ymin>817</ymin>
			<xmax>1876</xmax>
			<ymax>1239</ymax>
		</bndbox>
	</object>
	<object>
		<name>face</name>
		<truncated>0</truncated>
		<difficult>0</difficult>
		<jingai>1</jingai>
		<blur>0</blur>
		<pose>0</pose>
		<occlusion>0</occlusion>
		<bndbox>
			<xmin>1490</xmin>
			<ymin>494</ymin>
			<xmax>1671</xmax>
			<ymax>635</ymax>
		</bndbox>
	</object>
	<object>
		<name>face</name>
		<truncated>0</truncated>
		<difficult>0</difficult>
		<jingai>0</jingai>
		<blur>0</blur>
		<pose>0</pose>
		<occlusion>0</occlusion>
		<bndbox>
			<xmin>2396</xmin>
			<ymin>658</ymin>
			<xmax>2747</xmax>
			<ymax>1059</ymax>
		</bndbox>
	</object>
</annotation>
