<annotation>
	<folder>download</folder>
	<filename>2048554.jpg</filename>
	<path>D:\danbooru_face\download\2048554.jpg</path>
	<source>
		<database>Unknown</database>
	</source>
	<size>
		<width>1920</width>
		<height>1030</height>
		<depth>3</depth>
	</size>
	<segmented>0</segmented>
	<object>
		<name>face</name>
		<truncated>0</truncated>
		<difficult>0</difficult>
		<jingai>0</jingai>
		<blur>0</blur>
		<pose>0</pose>
		<occlusion>1</occlusion>
		<bndbox>
			<xmin>1369</xmin>
			<ymin>199</ymin>
			<xmax>1518</xmax>
			<ymax>346</ymax>
		</bndbox>
	</object>
</annotation>
