<annotation>
	<folder>download</folder>
	<filename>746804.jpg</filename>
	<path>C:\work\danbooru_face\download\746804.jpg</path>
	<source>
		<database>Unknown</database>
	</source>
	<size>
		<width>1231</width>
		<height>800</height>
		<depth>3</depth>
	</size>
	<segmented>0</segmented>
	<object>
		<name>face</name>
		<truncated>0</truncated>
		<difficult>0</difficult>
		<jingai>0</jingai>
		<blur>0</blur>
		<pose>0</pose>
		<occlusion>2</occlusion>
		<bndbox>
			<xmin>551</xmin>
			<ymin>78</ymin>
			<xmax>627</xmax>
			<ymax>179</ymax>
		</bndbox>
	</object>
	<object>
		<name>face</name>
		<truncated>0</truncated>
		<difficult>0</difficult>
		<jingai>0</jingai>
		<blur>0</blur>
		<pose>0</pose>
		<occlusion>0</occlusion>
		<bndbox>
			<xmin>866</xmin>
			<ymin>205</ymin>
			<xmax>937</xmax>
			<ymax>294</ymax>
		</bndbox>
	</object>
</annotation>
