<annotation>
	<folder>download</folder>
	<filename>815085.jpg</filename>
	<path>C:\work\danbooru_face\download\815085.jpg</path>
	<source>
		<database>Unknown</database>
	</source>
	<size>
		<width>1030</width>
		<height>920</height>
		<depth>3</depth>
	</size>
	<segmented>0</segmented>
	<object>
		<name>face</name>
		<truncated>0</truncated>
		<difficult>0</difficult>
		<jingai>0</jingai>
		<blur>0</blur>
		<pose>0</pose>
		<occlusion>0</occlusion>
		<bndbox>
			<xmin>386</xmin>
			<ymin>173</ymin>
			<xmax>566</xmax>
			<ymax>370</ymax>
		</bndbox>
	</object>
	<object>
		<name>face</name>
		<truncated>0</truncated>
		<difficult>0</difficult>
		<jingai>0</jingai>
		<blur>0</blur>
		<pose>0</pose>
		<occlusion>0</occlusion>
		<bndbox>
			<xmin>293</xmin>
			<ymin>619</ymin>
			<xmax>370</xmax>
			<ymax>671</ymax>
		</bndbox>
	</object>
	<object>
		<name>face</name>
		<truncated>0</truncated>
		<difficult>0</difficult>
		<jingai>1</jingai>
		<blur>0</blur>
		<pose>0</pose>
		<occlusion>0</occlusion>
		<bndbox>
			<xmin>37</xmin>
			<ymin>753</ymin>
			<xmax>78</xmax>
			<ymax>782</ymax>
		</bndbox>
	</object>
</annotation>
